shippinglabel_pypi/__init__.py
shippinglabel_pypi/py.typed
shippinglabel_pypi-0.1.0.post1.dist-info/LICENSE
shippinglabel_pypi-0.1.0.post1.dist-info/METADATA
shippinglabel_pypi-0.1.0.post1.dist-info/WHEEL
shippinglabel_pypi-0.1.0.post1.dist-info/entry_points.txt
shippinglabel_pypi-0.1.0.post1.dist-info/RECORD
